txtdata/__init__.py
txtdata/py.typed
txtdata-0.1.2.dist-info/LICENSE
txtdata-0.1.2.dist-info/METADATA
txtdata-0.1.2.dist-info/WHEEL
txtdata-0.1.2.dist-info/RECORD
